imaginenc/__init__.py
imaginenc/__main__.py
imaginenc/imaginenc.py
tests/__init__.py
tests/test_imaginenc.py
imaginenc-1.0.1.dist-info/LICENSE
imaginenc-1.0.1.dist-info/METADATA
imaginenc-1.0.1.dist-info/WHEEL
imaginenc-1.0.1.dist-info/entry_points.txt
imaginenc-1.0.1.dist-info/top_level.txt
imaginenc-1.0.1.dist-info/RECORD
