Metadata-Version: 2.1
Name: imaginenc
Version: 1.0.1
Summary: Convert any file into an image
Home-page: https://github.com/LordDeatHunter/Imaginenc
Author: LordDeatHunter
Author-email: desuhansa@gmail.com
License: UNKNOWN
Project-URL: Bug Tracker, https://github.com/LordDeatHunter/Imaginenc/issues
Platform: any
Classifier: Natural Language :: English
Classifier: Programming Language :: Python :: 3
Classifier: Programming Language :: Python :: 3.8
Classifier: Programming Language :: Python :: 3.9
Classifier: License :: OSI Approved :: MIT License
Classifier: Operating System :: OS Independent
Requires-Python: >=3.8
License-File: LICENSE
Requires-Dist: numpy (>=1.21.0)
Requires-Dist: Pillow (>=8.3.0)
